{
  "url": "https://api.github.com/repos/apiman/apiman/releases/84475818",
  "assets_url": "https://api.github.com/repos/apiman/apiman/releases/84475818/assets",
  "upload_url": "https://uploads.github.com/repos/apiman/apiman/releases/84475818/assets{?name,label}",
  "html_url": "https://github.com/apiman/apiman/releases/tag/3.0.0.Final",
  "id": 84475818,
  "author": {
    "login": "github-actions[bot]",
    "id": 41898282,
    "node_id": "MDM6Qm90NDE4OTgyODI=",
    "avatar_url": "https://avatars.githubusercontent.com/in/15368?v=4",
    "gravatar_id": "",
    "url": "https://api.github.com/users/github-actions%5Bbot%5D",
    "html_url": "https://github.com/apps/github-actions",
    "followers_url": "https://api.github.com/users/github-actions%5Bbot%5D/followers",
    "following_url": "https://api.github.com/users/github-actions%5Bbot%5D/following{/other_user}",
    "gists_url": "https://api.github.com/users/github-actions%5Bbot%5D/gists{/gist_id}",
    "starred_url": "https://api.github.com/users/github-actions%5Bbot%5D/starred{/owner}{/repo}",
    "subscriptions_url": "https://api.github.com/users/github-actions%5Bbot%5D/subscriptions",
    "organizations_url": "https://api.github.com/users/github-actions%5Bbot%5D/orgs",
    "repos_url": "https://api.github.com/users/github-actions%5Bbot%5D/repos",
    "events_url": "https://api.github.com/users/github-actions%5Bbot%5D/events{/privacy}",
    "received_events_url": "https://api.github.com/users/github-actions%5Bbot%5D/received_events",
    "type": "Bot",
    "site_admin": false
  },
  "node_id": "RE_kwDOALv6ss4FCP-q",
  "tag_name": "3.0.0.Final",
  "target_commitish": "master",
  "name": "3.0.0.Final",
  "draft": false,
  "prerelease": false,
  "created_at": "2022-11-29T16:41:58Z",
  "published_at": "2022-11-29T16:42:33Z",
  "assets": [
    {
      "url": "https://api.github.com/repos/apiman/apiman/releases/assets/86406008",
      "id": 86406008,
      "node_id": "RA_kwDOALv6ss4FJnN4",
      "name": "apiman-distro-tomcat-3.0.0.Final-overlay.zip",
      "label": null,
      "uploader": {
        "login": "msavy",
        "id": 423513,
        "node_id": "MDQ6VXNlcjQyMzUxMw==",
        "avatar_url": "https://avatars.githubusercontent.com/u/423513?v=4",
        "gravatar_id": "",
        "url": "https://api.github.com/users/msavy",
        "html_url": "https://github.com/msavy",
        "followers_url": "https://api.github.com/users/msavy/followers",
        "following_url": "https://api.github.com/users/msavy/following{/other_user}",
        "gists_url": "https://api.github.com/users/msavy/gists{/gist_id}",
        "starred_url": "https://api.github.com/users/msavy/starred{/owner}{/repo}",
        "subscriptions_url": "https://api.github.com/users/msavy/subscriptions",
        "organizations_url": "https://api.github.com/users/msavy/orgs",
        "repos_url": "https://api.github.com/users/msavy/repos",
        "events_url": "https://api.github.com/users/msavy/events{/privacy}",
        "received_events_url": "https://api.github.com/users/msavy/received_events",
        "type": "User",
        "site_admin": false
      },
      "content_type": "application/zip",
      "state": "uploaded",
      "size": 343222669,
      "download_count": 0,
      "created_at": "2022-11-29T20:03:14Z",
      "updated_at": "2022-11-29T20:16:07Z",
      "browser_download_url": "https://github.com/apiman/apiman/releases/download/3.0.0.Final/apiman-distro-tomcat-3.0.0.Final-overlay.zip"
    },
    {
      "url": "https://api.github.com/repos/apiman/apiman/releases/assets/86403750",
      "id": 86403750,
      "node_id": "RA_kwDOALv6ss4FJmqm",
      "name": "apiman-distro-vertx-3.0.0.Final.zip",
      "label": null,
      "uploader": {
        "login": "msavy",
        "id": 423513,
        "node_id": "MDQ6VXNlcjQyMzUxMw==",
        "avatar_url": "https://avatars.githubusercontent.com/u/423513?v=4",
        "gravatar_id": "",
        "url": "https://api.github.com/users/msavy",
        "html_url": "https://github.com/msavy",
        "followers_url": "https://api.github.com/users/msavy/followers",
        "following_url": "https://api.github.com/users/msavy/following{/other_user}",
        "gists_url": "https://api.github.com/users/msavy/gists{/gist_id}",
        "starred_url": "https://api.github.com/users/msavy/starred{/owner}{/repo}",
        "subscriptions_url": "https://api.github.com/users/msavy/subscriptions",
        "organizations_url": "https://api.github.com/users/msavy/orgs",
        "repos_url": "https://api.github.com/users/msavy/repos",
        "events_url": "https://api.github.com/users/msavy/events{/privacy}",
        "received_events_url": "https://api.github.com/users/msavy/received_events",
        "type": "User",
        "site_admin": false
      },
      "content_type": "application/zip",
      "state": "uploaded",
      "size": 97956787,
      "download_count": 0,
      "created_at": "2022-11-29T19:38:46Z",
      "updated_at": "2022-11-29T19:47:33Z",
      "browser_download_url": "https://github.com/apiman/apiman/releases/download/3.0.0.Final/apiman-distro-vertx-3.0.0.Final.zip"
    },
    {
      "url": "https://api.github.com/repos/apiman/apiman/releases/assets/86403764",
      "id": 86403764,
      "node_id": "RA_kwDOALv6ss4FJmq0",
      "name": "apiman-distro-wildfly-3.0.0.Final-overlay.zip",
      "label": null,
      "uploader": {
        "login": "msavy",
        "id": 423513,
        "node_id": "MDQ6VXNlcjQyMzUxMw==",
        "avatar_url": "https://avatars.githubusercontent.com/u/423513?v=4",
        "gravatar_id": "",
        "url": "https://api.github.com/users/msavy",
        "html_url": "https://github.com/msavy",
        "followers_url": "https://api.github.com/users/msavy/followers",
        "following_url": "https://api.github.com/users/msavy/following{/other_user}",
        "gists_url": "https://api.github.com/users/msavy/gists{/gist_id}",
        "starred_url": "https://api.github.com/users/msavy/starred{/owner}{/repo}",
        "subscriptions_url": "https://api.github.com/users/msavy/subscriptions",
        "organizations_url": "https://api.github.com/users/msavy/orgs",
        "repos_url": "https://api.github.com/users/msavy/repos",
        "events_url": "https://api.github.com/users/msavy/events{/privacy}",
        "received_events_url": "https://api.github.com/users/msavy/received_events",
        "type": "User",
        "site_admin": false
      },
      "content_type": "application/zip",
      "state": "uploaded",
      "size": 347085003,
      "download_count": 0,
      "created_at": "2022-11-29T19:38:56Z",
      "updated_at": "2022-11-29T20:01:36Z",
      "browser_download_url": "https://github.com/apiman/apiman/releases/download/3.0.0.Final/apiman-distro-wildfly-3.0.0.Final-overlay.zip"
    }
  ],
  "tarball_url": "https://api.github.com/repos/apiman/apiman/tarball/3.0.0.Final",
  "zipball_url": "https://api.github.com/repos/apiman/apiman/zipball/3.0.0.Final",
  "body": "Please refer to our comprehensive [changelog](https://github.com/apiman/apiman/blob/master/CHANGELOG.adoc#300final).\r\n\r\n![image](https://user-images.githubusercontent.com/423513/204639116-39b89946-22bd-4cc1-ae0f-afe28d38ed83.png)\r\n",
  "reactions": {
    "url": "https://api.github.com/repos/apiman/apiman/releases/84475818/reactions",
    "total_count": 1,
    "+1": 0,
    "-1": 0,
    "laugh": 0,
    "hooray": 0,
    "confused": 0,
    "heart": 0,
    "rocket": 1,
    "eyes": 0
  }
}
